PipePyper/PipePyper.py
PipePyper/__init__.py
PipePyper/mytools.py
PipePyper-2.4.2.dist-info/DESCRIPTION.rst
PipePyper-2.4.2.dist-info/METADATA
PipePyper-2.4.2.dist-info/RECORD
PipePyper-2.4.2.dist-info/WHEEL
PipePyper-2.4.2.dist-info/metadata.json
PipePyper-2.4.2.dist-info/top_level.txt
