Metadata-Version: 2.0
Name: PipePyper
Version: 2.4.2
Summary: multiThreading calculation FrameWork
Home-page: https://github.com/HongYuzhuang/PipePyper
Author: pyEric
Author-email: hongyz1993@163.com
License: UNKNOWN
Platform: UNKNOWN
